macha/__init__.py
macha/charmm_factory.py
macha/functions.py
macha/main.py
macha/setup.py
matcha_johannes-0.1.dist-info/LICENSE
matcha_johannes-0.1.dist-info/METADATA
matcha_johannes-0.1.dist-info/WHEEL
matcha_johannes-0.1.dist-info/top_level.txt
matcha_johannes-0.1.dist-info/RECORD
