Metadata-Version: 2.1
Name: matcha-johannes
Version: 0.1
Summary: A small example package
Author: Me
Author-email: Asmund Kaupang <asmund.kaupang@farmasi.uio.no>, Johannes Karwounopoulos <johannes.karwou@gmail.com>
License: Copyright (c) 2018 The Python Packaging Authority        
Project-URL: Homepage, https://github.com/pypa/sampleproject
Project-URL: Bug Tracker, https://github.com/pypa/sampleproject/issues
Classifier: Programming Language :: Python :: 3
Classifier: License :: OSI Approved :: MIT License
Classifier: Operating System :: OS Independent
Requires-Python: >=3.7
License-File: LICENSE
